polono_p31s/__init__.py
polono_p31s/cli.py
polono_p31s/printer.py
polono_p31s/py.typed
polono_p31s-0.1.0.dist-info/METADATA
polono_p31s-0.1.0.dist-info/WHEEL
polono_p31s-0.1.0.dist-info/entry_points.txt
polono_p31s-0.1.0.dist-info/licenses/LICENSE
polono_p31s-0.1.0.dist-info/RECORD
