Metadata-Version: 2.4
Name: polono-p31s
Version: 0.1.0
Summary: Python library for Polono P31S thermal label printer via BLE
Project-URL: Homepage, https://github.com/andyq/polono-p31s
Project-URL: Repository, https://github.com/andyq/polono-p31s
Author: Andy
License: MIT
License-File: LICENSE
Keywords: ble,bluetooth,label,p31s,polono,printer,thermal
Classifier: Development Status :: 4 - Beta
Classifier: Intended Audience :: Developers
Classifier: License :: OSI Approved :: MIT License
Classifier: Operating System :: OS Independent
Classifier: Programming Language :: Python :: 3
Classifier: Programming Language :: Python :: 3.10
Classifier: Programming Language :: Python :: 3.11
Classifier: Programming Language :: Python :: 3.12
Classifier: Topic :: Printing
Requires-Python: >=3.10
Requires-Dist: bleak>=0.21.0
Requires-Dist: click>=8.0.0
Requires-Dist: pillow>=10.0.0
Requires-Dist: python-barcode>=0.15.0
Requires-Dist: qrcode>=7.0
Requires-Dist: rich>=13.0.0
